MANIFEST.in
README.md
setup.cfg
setup.py
bin/lem
lem/__init__.py
lem/configuration.py
lem/main.py
lem.egg-info/PKG-INFO
lem.egg-info/SOURCES.txt
lem.egg-info/dependency_links.txt
lem.egg-info/requires.txt
lem.egg-info/top_level.txt
lem/config/lem.conf
lem/exploit/__init__.py
lem/exploit/curated_exploit.py
lem/exploit/curation_manager.py
lem/exploit/exploit_source.py
lem/host/__init__.py
lem/host/assessor.py
lem/host/patcher.py
lem/score/__init__.py
lem/score/score.py
lem/score/score_manager.py
lem/vulnerability/__init__.py
lem/vulnerability/security_api_source.py
lem/vulnerability/vulnerability_manager.py
lem/vulnerability/vulnerability_source.py